prompt_studio_python/__init__.py
prompt_studio_python/base.py
prompt_studio_python/cli.py
prompt_studio_python/prompt/__init__.py
prompt_studio_python/prompt/cache.py
prompt_studio_python/prompt/types.py
prompt_studio_python/utils/__init__.py
prompt_studio_python/utils/helpers.py
tests/__init__.py
tests/conftest.py
tests/test_base.py
tests/test_cache.py
tests/test_prompt_manager.py
prompt_studio_python-0.1.0.dist-info/LICENSE
prompt_studio_python-0.1.0.dist-info/METADATA
prompt_studio_python-0.1.0.dist-info/WHEEL
prompt_studio_python-0.1.0.dist-info/top_level.txt
prompt_studio_python-0.1.0.dist-info/RECORD
