Metadata-Version: 2.1
Name: prompt_studio_python
Version: 0.1.0
Summary: A Python SDK for Prompt Studio
Home-page: https://github.com/promptstudio/promptstudio-python-sdk
Author: PromptStudio
Author-email: Your Name <your.email@example.com>
Project-URL: Homepage, https://github.com/promptstudio/promptstudio-python-sdk
Project-URL: Bug Tracker, https://github.com/promptstudio/promptstudio-python-sdk/issues
Classifier: Programming Language :: Python :: 3
Classifier: License :: OSI Approved :: MIT License
Classifier: Operating System :: OS Independent
Requires-Python: >=3.9
License-File: LICENSE
Requires-Dist: aiohttp
Requires-Dist: pydantic
Requires-Dist: openai
Requires-Dist: anthropic
Requires-Dist: google-generativeai
Requires-Dist: fastapi
